classroom_utils/__init__.py
classroom_utils/__main__.py
classroom_utils/_version.py
classroom_utils/ascii_art.py
classroom_utils/classes.py
classroom_utils/cli.py
classroom_utils/config.py
classroom_utils/dialogs.py
classroom_utils/github_operations.py
classroom_utils/local_operations.py
classroom_utils/main.py
classroom_utils/subcommands.py
classroom_utils/resources/schemas/classlist_file_schema.json
classroom_utils/resources/schemas/config_file_schema.json
classroom_utils-0.4.1.dist-info/LICENSE
classroom_utils-0.4.1.dist-info/METADATA
classroom_utils-0.4.1.dist-info/WHEEL
classroom_utils-0.4.1.dist-info/entry_points.txt
classroom_utils-0.4.1.dist-info/top_level.txt
classroom_utils-0.4.1.dist-info/RECORD
