Metadata-Version: 2.1
Name: classroom_utils
Version: 0.4.1
Summary: Utilities to handle stuff likes github orgs for classes.
Home-page: https://github.com/twyleg/classroom_utils
Author: Torsten Wylegala
Author-email: mail@twyleg.de
License: GPL 3.0
Keywords: class classroom github edu education
License-File: LICENSE
Requires-Dist: jsonschema~=4.21.1
Requires-Dist: PyGithub~=2.2.0
Requires-Dist: GitPython~=3.1.42
Requires-Dist: inquirerpy~=0.3.4
Requires-Dist: alive-progress~=3.1.5
Requires-Dist: prompt-toolkit~=3.0.43
